toxicblend/__init__.py
toxicblend/toxicblend_pb2.py
toxicblend/toxicblend_pb2_grpc.py
toxicblend-0.2.0.dist-info/LICENSE
toxicblend-0.2.0.dist-info/METADATA
toxicblend-0.2.0.dist-info/WHEEL
toxicblend-0.2.0.dist-info/top_level.txt
toxicblend-0.2.0.dist-info/RECORD
