Metadata-Version: 2.1
Name: toxicblend
Version: 0.2.0
Summary: Generated protobuffer files for https://crates.io/crates/toxicblend
Home-page: https://crates.io/crates/toxicblend
Author: Eadf
Author-email: lacklustr@protonmail.com
License: AGPL-3.0
Platform: UNKNOWN
Classifier: Development Status :: 1 - Planning
Classifier: Intended Audience :: End Users/Desktop
Classifier: License :: OSI Approved :: GNU Affero General Public License v3 or later (AGPLv3+)
Classifier: Operating System :: OS Independent
Classifier: Topic :: Multimedia :: Graphics
Classifier: Programming Language :: Python :: 3.7
Classifier: Programming Language :: Python :: 3.8
Classifier: Programming Language :: Python :: 3.9
Classifier: Programming Language :: Python :: 3.10
Requires-Dist: protobuf (>=3.15)
Requires-Dist: grpcio (>=1.37)
